CointArbitrage/__init__.py
CointArbitrage/instant_with_wind/__init__.py
CointArbitrage/instant_with_wind/instant.py
CointArbitrage/instant_with_wind/load_wind.py
CointArbitrage/instant_with_wind/position_with_constrain.py
CointArbitrage/instant_with_wind/tail.py
CointArbitrage/pairing_period/CointTest.py
CointArbitrage/pairing_period/__init__.py
CointArbitrage/pairing_period/filter.py
CointArbitrage/trading_period/__init__.py
CointArbitrage/trading_period/trading.py
CointArbitrage/trading_period/zscore.py
CointArbitrage-0.0.63.dist-info/DESCRIPTION.rst
CointArbitrage-0.0.63.dist-info/METADATA
CointArbitrage-0.0.63.dist-info/RECORD
CointArbitrage-0.0.63.dist-info/WHEEL
CointArbitrage-0.0.63.dist-info/metadata.json
CointArbitrage-0.0.63.dist-info/top_level.txt
