Metadata-Version: 2.0
Name: CointArbitrage
Version: 0.0.63
Summary: Conintegration method
Home-page: UNKNOWN
Author: Yili Peng
Author-email: yili_peng@outlook.com
License: UNKNOWN
Platform: UNKNOWN
Requires-Dist: RNWS
Requires-Dist: mini-exchange
